flask_appcache.py
setup.py
Flask_Appcache.egg-info/PKG-INFO
Flask_Appcache.egg-info/SOURCES.txt
Flask_Appcache.egg-info/dependency_links.txt
Flask_Appcache.egg-info/not-zip-safe
Flask_Appcache.egg-info/requires.txt
Flask_Appcache.egg-info/top_level.txt