Metadata-Version: 1.1
Name: Flask-Appcache
Version: 0.1.2
Summary: Semi-automagically sets up appcache for you
Home-page: https://github.com/shuhaowu/flask-appcache/
Author: Shuhao Wu
Author-email: shuhao@shuhaowu.com
License: MPLv2
Platform: any
Classifier: Environment :: Web Environment
Classifier: Intended Audience :: Developers
Classifier: License :: OSI Approved :: Mozilla Public License 2.0 (MPL 2.0)
Classifier: Operating System :: OS Independent
Classifier: Programming Language :: Python
Classifier: Topic :: Internet :: WWW/HTTP :: Dynamic Content
Classifier: Topic :: Software Development :: Libraries :: Python Modules
